kebab/__init__.py
kebab/aws.py
kebab/cli/__init__.py
kebab/cli/cli.py
kebab/constants.py
kebab/exceptions.py
kebab/k8s.py
kebab/loaders.py
kebab/magic.py
kebab/openers.py
kebab/sources.py
kebab/utils.py
pykebab-0.10.2.dist-info/METADATA
pykebab-0.10.2.dist-info/WHEEL
pykebab-0.10.2.dist-info/entry_points.txt
pykebab-0.10.2.dist-info/RECORD
